pytarot/__init__.py
pytarot/__main__.py
pytarot/answersofwisdom.py
pytarot/luckyday.py
pytarot/positive_action.py
pytarot/truelover.py
pytarot-0.1.1.dist-info/LICENSE
pytarot-0.1.1.dist-info/METADATA
pytarot-0.1.1.dist-info/WHEEL
pytarot-0.1.1.dist-info/entry_points.txt
pytarot-0.1.1.dist-info/top_level.txt
pytarot-0.1.1.dist-info/RECORD
