Metadata-Version: 2.1
Name: pytarot
Version: 0.1.1
Summary: A package that provides fortune telling features, developed with pyenv, built with build using setuptools, uploaded to PyPI using twine, and distributed via pip.
Author-email: Annabeth Gao <mg6839@nyu.edu>, Boming Zhang <bz2196@nyu.edu>, Jack Zhang <bz2196@nyu.edu>
License: GNU GENERAL PUBLIC LICENSE
Project-URL: Homepage, https://github.com/nyu-software-engineering/python-package-example
Project-URL: Repository, https://github.com/nyu-software-engineering/python-package-example.git
Project-URL: Bug Tracker, https://github.com/nyu-software-engineering/python-package-example/issues
Keywords: python,package,build
Classifier: Programming Language :: Python :: 3
Classifier: Intended Audience :: Education
Classifier: License :: OSI Approved :: GNU General Public License v3 (GPLv3)
Classifier: Operating System :: OS Independent
Requires-Python: >=3.7
License-File: LICENSE
Provides-Extra: dev
Requires-Dist: pytest; extra == "dev"
